infisical_api.py
infisical_api-1.0.3.dist-info/METADATA
infisical_api-1.0.3.dist-info/WHEEL
infisical_api-1.0.3.dist-info/licenses/LICENSE
infisical_api-1.0.3.dist-info/RECORD
