Metadata-Version: 2.4
Name: infisical_api
Version: 1.0.3
Summary: Infisical Client using REST API
Author-email: Justin Kumpe <jakumpe@kumpes.com>
License-Expression: GPL-3.0
License-File: LICENSE
Classifier: License :: OSI Approved :: GNU General Public License v3 (GPLv3)
Classifier: Natural Language :: English
Classifier: Operating System :: OS Independent
Classifier: Programming Language :: Python :: 3
Requires-Python: >=3.7
Requires-Dist: requests
